{
  "20210221002602": {
    "Bestätigte Fälle": 50192,
    "Erstimpfungen": 76926,
    "Zweitimpfungen": 43061,
    "Todesfälle": 1216,
    "Patienten in klinischer Behandlung": {
      "Stationär gesamt": 306,
      "Normalstation gesamt": 231,
      "Normalstation aus Hamburg": 192,
      "Intensiv gesamt": 75,
      "Intensiv aus Hamburg": 61
    },
    "Verteilung der Infizierten nach Alter und Geschlecht": {
      "bis 5 Jahre": {
        "männlich": 642,
        "weiblich": 533
      },
      "unbekannt": 389,
      "6 bis 14 Jahre": {
        "männlich": 1448,
        "weiblich": 1297
      },
      "15 bis 19 Jahre": {
        "männlich": 1420,
        "weiblich": 1413
      },
      "20 bis 29 Jahre": {
        "männlich": 4604,
        "weiblich": 4792
      },
      "30 bis 39 Jahre": {
        "männlich": 4187,
        "weiblich": 4467
      },
      "40 bis 49 Jahre": {
        "männlich": 3384,
        "weiblich": 3729
      },
      "50 bis 59 Jahre": {
        "männlich": 3382,
        "weiblich": 3378
      },
      "60 bis 69 Jahre": {
        "männlich": 1790,
        "weiblich": 1654
      },
      "70 bis 79 Jahre": {
        "männlich": 1248,
        "weiblich": 1304
      },
      "80 bis 89 Jahre": {
        "männlich": 1103,
        "weiblich": 1808
      },
      "über 90 Jahre": {
        "männlich": 261,
        "weiblich": 945
      }
    },
    "Entwicklung der Zahl der positiv auf COVID-19 getesteten Personen nach Bezirken": {
      "Altona": {
        "Fallzahlen": 6685
      },
      "Bergedorf": {
        "Fallzahlen": 3218
      },
      "Eimsbüttel": {
        "Fallzahlen": 5547
      },
      "Hamburg Mitte": {
        "Fallzahlen": 10649
      },
      "Hamburg Nord": {
        "Fallzahlen": 6613
      },
      "Harburg": {
        "Fallzahlen": 4784
      },
      "Wandsbek": {
        "Fallzahlen": 11682
      }
    }
  },
  "20210222115928": {
    "Bestätigte Fälle": 50524,
    "Erstimpfungen": 82242,
    "Zweitimpfungen": 44976,
    "Todesfälle": 1223,
    "Patienten in klinischer Behandlung": {
      "Stationär gesamt": 306,
      "Normalstation gesamt": 231,
      "Normalstation aus Hamburg": 192,
      "Intensiv gesamt": 75,
      "Intensiv aus Hamburg": 61
    },
    "Verteilung der Infizierten nach Alter und Geschlecht": {
      "bis 5 Jahre": {
        "männlich": 642,
        "weiblich": 533
      },
      "unbekannt": 389,
      "6 bis 14 Jahre": {
        "männlich": 1448,
        "weiblich": 1297
      },
      "15 bis 19 Jahre": {
        "männlich": 1420,
        "weiblich": 1413
      },
      "20 bis 29 Jahre": {
        "männlich": 4604,
        "weiblich": 4792
      },
      "30 bis 39 Jahre": {
        "männlich": 4187,
        "weiblich": 4467
      },
      "40 bis 49 Jahre": {
        "männlich": 3384,
        "weiblich": 3729
      },
      "50 bis 59 Jahre": {
        "männlich": 3382,
        "weiblich": 3378
      },
      "60 bis 69 Jahre": {
        "männlich": 1790,
        "weiblich": 1654
      },
      "70 bis 79 Jahre": {
        "männlich": 1248,
        "weiblich": 1304
      },
      "80 bis 89 Jahre": {
        "männlich": 1103,
        "weiblich": 1808
      },
      "über 90 Jahre": {
        "männlich": 261,
        "weiblich": 945
      }
    },
    "Entwicklung der Zahl der positiv auf COVID-19 getesteten Personen nach Bezirken": {
      "Altona": {
        "Fallzahlen": 6685
      },
      "Bergedorf": {
        "Fallzahlen": 3218
      },
      "Eimsbüttel": {
        "Fallzahlen": 5547
      },
      "Hamburg Mitte": {
        "Fallzahlen": 10649
      },
      "Hamburg Nord": {
        "Fallzahlen": 6613
      },
      "Harburg": {
        "Fallzahlen": 4784
      },
      "Wandsbek": {
        "Fallzahlen": 11682
      }
    }
  },
  "20210223131950": {
    "Bestätigte Fälle": 50685,
    "Erstimpfungen": 84688,
    "Zweitimpfungen": 46893,
    "Todesfälle": 1224,
    "Patienten in klinischer Behandlung": {
      "Stationär gesamt": 310,
      "Normalstation gesamt": 234,
      "Normalstation aus Hamburg": 190,
      "Intensiv gesamt": 76,
      "Intensiv aus Hamburg": 63
    },
    "Verteilung der Infizierten nach Alter und Geschlecht": {
      "bis 5 Jahre": {
        "männlich": 667,
        "weiblich": 558
      },
      "unbekannt": 401,
      "6 bis 14 Jahre": {
        "männlich": 1477,
        "weiblich": 1339
      },
      "15 bis 19 Jahre": {
        "männlich": 1452,
        "weiblich": 1447
      },
      "20 bis 29 Jahre": {
        "männlich": 4742,
        "weiblich": 4910
      },
      "30 bis 39 Jahre": {
        "männlich": 4320,
        "weiblich": 4584
      },
      "40 bis 49 Jahre": {
        "männlich": 3481,
        "weiblich": 3815
      },
      "50 bis 59 Jahre": {
        "männlich": 3487,
        "weiblich": 3477
      },
      "60 bis 69 Jahre": {
        "männlich": 1866,
        "weiblich": 1703
      },
      "70 bis 79 Jahre": {
        "männlich": 1286,
        "weiblich": 1332
      },
      "80 bis 89 Jahre": {
        "männlich": 1126,
        "weiblich": 1837
      },
      "über 90 Jahre": {
        "männlich": 264,
        "weiblich": 953
      }
    },
    "Entwicklung der Zahl der positiv auf COVID-19 getesteten Personen nach Bezirken": {
      "Altona": {
        "Fallzahlen": 6836
      },
      "Bergedorf": {
        "Fallzahlen": 3335
      },
      "Eimsbüttel": {
        "Fallzahlen": 5680
      },
      "Hamburg Mitte": {
        "Fallzahlen": 10961
      },
      "Hamburg Nord": {
        "Fallzahlen": 6849
      },
      "Harburg": {
        "Fallzahlen": 4922
      },
      "Wandsbek": {
        "Fallzahlen": 11939
      }
    }
  },
  "20210223135959": {
    "Bestätigte Fälle": 50685,
    "Erstimpfungen": 84688,
    "Zweitimpfungen": 46893,
    "Todesfälle": 1224,
    "Patienten in klinischer Behandlung": {
      "Stationär gesamt": 310,
      "Normalstation gesamt": 234,
      "Normalstation aus Hamburg": 190,
      "Intensiv gesamt": 76,
      "Intensiv aus Hamburg": 63
    },
    "Verteilung der Infizierten nach Alter und Geschlecht": {
      "bis 5 Jahre": {
        "männlich": 667,
        "weiblich": 558
      },
      "unbekannt": 401,
      "6 bis 14 Jahre": {
        "männlich": 1477,
        "weiblich": 1339
      },
      "15 bis 19 Jahre": {
        "männlich": 1452,
        "weiblich": 1447
      },
      "20 bis 29 Jahre": {
        "männlich": 4742,
        "weiblich": 4910
      },
      "30 bis 39 Jahre": {
        "männlich": 4320,
        "weiblich": 4584
      },
      "40 bis 49 Jahre": {
        "männlich": 3481,
        "weiblich": 3815
      },
      "50 bis 59 Jahre": {
        "männlich": 3487,
        "weiblich": 3477
      },
      "60 bis 69 Jahre": {
        "männlich": 1866,
        "weiblich": 1703
      },
      "70 bis 79 Jahre": {
        "männlich": 1286,
        "weiblich": 1332
      },
      "80 bis 89 Jahre": {
        "männlich": 1126,
        "weiblich": 1837
      },
      "über 90 Jahre": {
        "männlich": 264,
        "weiblich": 953
      }
    },
    "Entwicklung der Zahl der positiv auf COVID-19 getesteten Personen nach Bezirken": {
      "Altona": {
        "Fallzahlen": 6836
      },
      "Bergedorf": {
        "Fallzahlen": 3335
      },
      "Eimsbüttel": {
        "Fallzahlen": 5680
      },
      "Hamburg Mitte": {
        "Fallzahlen": 10961
      },
      "Hamburg Nord": {
        "Fallzahlen": 6849
      },
      "Harburg": {
        "Fallzahlen": 4922
      },
      "Wandsbek": {
        "Fallzahlen": 11939
      }
    }
  },
  "20210223204714": {
    "Bestätigte Fälle": 50685,
    "Erstimpfungen": 84688,
    "Zweitimpfungen": 46893,
    "Todesfälle": 1224,
    "Patienten in klinischer Behandlung": {
      "Stationär gesamt": 310,
      "Normalstation gesamt": 234,
      "Normalstation aus Hamburg": 190,
      "Intensiv gesamt": 76,
      "Intensiv aus Hamburg": 63
    },
    "Verteilung der Infizierten nach Alter und Geschlecht": {
      "bis 5 Jahre": {
        "männlich": 667,
        "weiblich": 558
      },
      "unbekannt": 401,
      "6 bis 14 Jahre": {
        "männlich": 1477,
        "weiblich": 1339
      },
      "15 bis 19 Jahre": {
        "männlich": 1452,
        "weiblich": 1447
      },
      "20 bis 29 Jahre": {
        "männlich": 4742,
        "weiblich": 4910
      },
      "30 bis 39 Jahre": {
        "männlich": 4320,
        "weiblich": 4584
      },
      "40 bis 49 Jahre": {
        "männlich": 3481,
        "weiblich": 3815
      },
      "50 bis 59 Jahre": {
        "männlich": 3487,
        "weiblich": 3477
      },
      "60 bis 69 Jahre": {
        "männlich": 1866,
        "weiblich": 1703
      },
      "70 bis 79 Jahre": {
        "männlich": 1286,
        "weiblich": 1332
      },
      "80 bis 89 Jahre": {
        "männlich": 1126,
        "weiblich": 1837
      },
      "über 90 Jahre": {
        "männlich": 264,
        "weiblich": 953
      }
    },
    "Entwicklung der Zahl der positiv auf COVID-19 getesteten Personen nach Bezirken": {
      "Altona": {
        "Fallzahlen": 6836
      },
      "Bergedorf": {
        "Fallzahlen": 3335
      },
      "Eimsbüttel": {
        "Fallzahlen": 5680
      },
      "Hamburg Mitte": {
        "Fallzahlen": 10961
      },
      "Hamburg Nord": {
        "Fallzahlen": 6849
      },
      "Harburg": {
        "Fallzahlen": 4922
      },
      "Wandsbek": {
        "Fallzahlen": 11939
      }
    }
  },
  "20210225184624": {
    "Bestätigte Fälle": 51274,
    "Erstimpfungen": 89986,
    "Zweitimpfungen": 49847,
    "Todesfälle": 1251,
    "Patienten in klinischer Behandlung": {
      "Stationär gesamt": 290,
      "Normalstation gesamt": 200,
      "Normalstation aus Hamburg": 166,
      "Intensiv gesamt": 90,
      "Intensiv aus Hamburg": 76
    },
    "Verteilung der Infizierten nach Alter und Geschlecht": {
      "bis 5 Jahre": {
        "männlich": 667,
        "weiblich": 558
      },
      "unbekannt": 401,
      "6 bis 14 Jahre": {
        "männlich": 1477,
        "weiblich": 1339
      },
      "15 bis 19 Jahre": {
        "männlich": 1452,
        "weiblich": 1447
      },
      "20 bis 29 Jahre": {
        "männlich": 4742,
        "weiblich": 4910
      },
      "30 bis 39 Jahre": {
        "männlich": 4320,
        "weiblich": 4584
      },
      "40 bis 49 Jahre": {
        "männlich": 3481,
        "weiblich": 3815
      },
      "50 bis 59 Jahre": {
        "männlich": 3487,
        "weiblich": 3477
      },
      "60 bis 69 Jahre": {
        "männlich": 1866,
        "weiblich": 1703
      },
      "70 bis 79 Jahre": {
        "männlich": 1286,
        "weiblich": 1332
      },
      "80 bis 89 Jahre": {
        "männlich": 1126,
        "weiblich": 1837
      },
      "über 90 Jahre": {
        "männlich": 264,
        "weiblich": 953
      }
    },
    "Entwicklung der Zahl der positiv auf COVID-19 getesteten Personen nach Bezirken": {
      "Altona": {
        "Fallzahlen": 6836
      },
      "Bergedorf": {
        "Fallzahlen": 3335
      },
      "Eimsbüttel": {
        "Fallzahlen": 5680
      },
      "Hamburg Mitte": {
        "Fallzahlen": 10961
      },
      "Hamburg Nord": {
        "Fallzahlen": 6849
      },
      "Harburg": {
        "Fallzahlen": 4922
      },
      "Wandsbek": {
        "Fallzahlen": 11939
      }
    }
  },
  "20210226204816": {
    "Bestätigte Fälle": 51462,
    "Erstimpfungen": 92826,
    "Zweitimpfungen": 50952,
    "Todesfälle": 1257,
    "Patienten in klinischer Behandlung": {
      "Stationär gesamt": 287,
      "Normalstation gesamt": 201,
      "Normalstation aus Hamburg": 168,
      "Intensiv gesamt": 86,
      "Intensiv aus Hamburg": 73
    },
    "Verteilung der Infizierten nach Alter und Geschlecht": {
      "bis 5 Jahre": {
        "männlich": 667,
        "weiblich": 558
      },
      "unbekannt": 401,
      "6 bis 14 Jahre": {
        "männlich": 1477,
        "weiblich": 1339
      },
      "15 bis 19 Jahre": {
        "männlich": 1452,
        "weiblich": 1447
      },
      "20 bis 29 Jahre": {
        "männlich": 4742,
        "weiblich": 4910
      },
      "30 bis 39 Jahre": {
        "männlich": 4320,
        "weiblich": 4584
      },
      "40 bis 49 Jahre": {
        "männlich": 3481,
        "weiblich": 3815
      },
      "50 bis 59 Jahre": {
        "männlich": 3487,
        "weiblich": 3477
      },
      "60 bis 69 Jahre": {
        "männlich": 1866,
        "weiblich": 1703
      },
      "70 bis 79 Jahre": {
        "männlich": 1286,
        "weiblich": 1332
      },
      "80 bis 89 Jahre": {
        "männlich": 1126,
        "weiblich": 1837
      },
      "über 90 Jahre": {
        "männlich": 264,
        "weiblich": 953
      }
    },
    "Entwicklung der Zahl der positiv auf COVID-19 getesteten Personen nach Bezirken": {
      "Altona": {
        "Fallzahlen": 6836
      },
      "Bergedorf": {
        "Fallzahlen": 3335
      },
      "Eimsbüttel": {
        "Fallzahlen": 5680
      },
      "Hamburg Mitte": {
        "Fallzahlen": 10961
      },
      "Hamburg Nord": {
        "Fallzahlen": 6849
      },
      "Harburg": {
        "Fallzahlen": 4922
      },
      "Wandsbek": {
        "Fallzahlen": 11939
      }
    }
  },
  "20210228022023": {
    "Bestätigte Fälle": 51665,
    "Erstimpfungen": 96003,
    "Zweitimpfungen": 51868,
    "Todesfälle": 1263,
    "Patienten in klinischer Behandlung": {
      "Stationär gesamt": 282,
      "Normalstation gesamt": 201,
      "Normalstation aus Hamburg": 160,
      "Intensiv gesamt": 81,
      "Intensiv aus Hamburg": 68
    },
    "Verteilung der Infizierten nach Alter und Geschlecht": {
      "bis 5 Jahre": {
        "männlich": 667,
        "weiblich": 558
      },
      "unbekannt": 401,
      "6 bis 14 Jahre": {
        "männlich": 1477,
        "weiblich": 1339
      },
      "15 bis 19 Jahre": {
        "männlich": 1452,
        "weiblich": 1447
      },
      "20 bis 29 Jahre": {
        "männlich": 4742,
        "weiblich": 4910
      },
      "30 bis 39 Jahre": {
        "männlich": 4320,
        "weiblich": 4584
      },
      "40 bis 49 Jahre": {
        "männlich": 3481,
        "weiblich": 3815
      },
      "50 bis 59 Jahre": {
        "männlich": 3487,
        "weiblich": 3477
      },
      "60 bis 69 Jahre": {
        "männlich": 1866,
        "weiblich": 1703
      },
      "70 bis 79 Jahre": {
        "männlich": 1286,
        "weiblich": 1332
      },
      "80 bis 89 Jahre": {
        "männlich": 1126,
        "weiblich": 1837
      },
      "über 90 Jahre": {
        "männlich": 264,
        "weiblich": 953
      }
    },
    "Entwicklung der Zahl der positiv auf COVID-19 getesteten Personen nach Bezirken": {
      "Altona": {
        "Fallzahlen": 6836
      },
      "Bergedorf": {
        "Fallzahlen": 3335
      },
      "Eimsbüttel": {
        "Fallzahlen": 5680
      },
      "Hamburg Mitte": {
        "Fallzahlen": 10961
      },
      "Hamburg Nord": {
        "Fallzahlen": 6849
      },
      "Harburg": {
        "Fallzahlen": 4922
      },
      "Wandsbek": {
        "Fallzahlen": 11939
      }
    }
  },
  "20210228193304": {
    "Bestätigte Fälle": 51791,
    "Erstimpfungen": 96003,
    "Zweitimpfungen": 51868,
    "Todesfälle": 1270,
    "Patienten in klinischer Behandlung": {
      "Stationär gesamt": 282,
      "Normalstation gesamt": 201,
      "Normalstation aus Hamburg": 160,
      "Intensiv gesamt": 81,
      "Intensiv aus Hamburg": 68
    },
    "Verteilung der Infizierten nach Alter und Geschlecht": {
      "bis 5 Jahre": {
        "männlich": 667,
        "weiblich": 558
      },
      "unbekannt": 401,
      "6 bis 14 Jahre": {
        "männlich": 1477,
        "weiblich": 1339
      },
      "15 bis 19 Jahre": {
        "männlich": 1452,
        "weiblich": 1447
      },
      "20 bis 29 Jahre": {
        "männlich": 4742,
        "weiblich": 4910
      },
      "30 bis 39 Jahre": {
        "männlich": 4320,
        "weiblich": 4584
      },
      "40 bis 49 Jahre": {
        "männlich": 3481,
        "weiblich": 3815
      },
      "50 bis 59 Jahre": {
        "männlich": 3487,
        "weiblich": 3477
      },
      "60 bis 69 Jahre": {
        "männlich": 1866,
        "weiblich": 1703
      },
      "70 bis 79 Jahre": {
        "männlich": 1286,
        "weiblich": 1332
      },
      "80 bis 89 Jahre": {
        "männlich": 1126,
        "weiblich": 1837
      },
      "über 90 Jahre": {
        "männlich": 264,
        "weiblich": 953
      }
    },
    "Entwicklung der Zahl der positiv auf COVID-19 getesteten Personen nach Bezirken": {
      "Altona": {
        "Fallzahlen": 6836
      },
      "Bergedorf": {
        "Fallzahlen": 3335
      },
      "Eimsbüttel": {
        "Fallzahlen": 5680
      },
      "Hamburg Mitte": {
        "Fallzahlen": 10961
      },
      "Hamburg Nord": {
        "Fallzahlen": 6849
      },
      "Harburg": {
        "Fallzahlen": 4922
      },
      "Wandsbek": {
        "Fallzahlen": 11939
      }
    }
  },
  "20210302135034": {
    "Bestätigte Fälle": 52232,
    "Erstimpfungen": 102636,
    "Zweitimpfungen": 53887,
    "Todesfälle": 1278,
    "Patienten in klinischer Behandlung": {
      "Stationär gesamt": 269,
      "Normalstation gesamt": 184,
      "Normalstation aus Hamburg": 149,
      "Intensiv gesamt": 85,
      "Intensiv aus Hamburg": 69
    },
    "Verteilung der Infizierten nach Alter und Geschlecht": {
      "bis 5 Jahre": {
        "männlich": 691,
        "weiblich": 593
      },
      "unbekannt": 408,
      "6 bis 14 Jahre": {
        "männlich": 1519,
        "weiblich": 1388
      },
      "15 bis 19 Jahre": {
        "männlich": 1501,
        "weiblich": 1487
      },
      "20 bis 29 Jahre": {
        "männlich": 4869,
        "weiblich": 5049
      },
      "30 bis 39 Jahre": {
        "männlich": 4481,
        "weiblich": 4734
      },
      "40 bis 49 Jahre": {
        "männlich": 3588,
        "weiblich": 3936
      },
      "50 bis 59 Jahre": {
        "männlich": 3599,
        "weiblich": 3593
      },
      "60 bis 69 Jahre": {
        "männlich": 1923,
        "weiblich": 1768
      },
      "70 bis 79 Jahre": {
        "männlich": 1318,
        "weiblich": 1366
      },
      "80 bis 89 Jahre": {
        "männlich": 1145,
        "weiblich": 1868
      },
      "über 90 Jahre": {
        "männlich": 265,
        "weiblich": 960
      }
    },
    "Entwicklung der Zahl der positiv auf COVID-19 getesteten Personen nach Bezirken": {
      "Altona": {
        "Fallzahlen": 7011
      },
      "Bergedorf": {
        "Fallzahlen": 3477
      },
      "Eimsbüttel": {
        "Fallzahlen": 5829
      },
      "Hamburg Mitte": {
        "Fallzahlen": 11317
      },
      "Hamburg Nord": {
        "Fallzahlen": 7055
      },
      "Harburg": {
        "Fallzahlen": 5125
      },
      "Wandsbek": {
        "Fallzahlen": 12235
      }
    }
  },
  "20210302235027": {
    "Bestätigte Fälle": 52232,
    "Erstimpfungen": 102636,
    "Zweitimpfungen": 53887,
    "Todesfälle": 1278,
    "Patienten in klinischer Behandlung": {
      "Stationär gesamt": 269,
      "Normalstation gesamt": 184,
      "Normalstation aus Hamburg": 149,
      "Intensiv gesamt": 85,
      "Intensiv aus Hamburg": 69
    },
    "Verteilung der Infizierten nach Alter und Geschlecht": {
      "bis 5 Jahre": {
        "männlich": 691,
        "weiblich": 593
      },
      "unbekannt": 408,
      "6 bis 14 Jahre": {
        "männlich": 1519,
        "weiblich": 1388
      },
      "15 bis 19 Jahre": {
        "männlich": 1501,
        "weiblich": 1487
      },
      "20 bis 29 Jahre": {
        "männlich": 4869,
        "weiblich": 5049
      },
      "30 bis 39 Jahre": {
        "männlich": 4481,
        "weiblich": 4734
      },
      "40 bis 49 Jahre": {
        "männlich": 3588,
        "weiblich": 3936
      },
      "50 bis 59 Jahre": {
        "männlich": 3599,
        "weiblich": 3593
      },
      "60 bis 69 Jahre": {
        "männlich": 1923,
        "weiblich": 1768
      },
      "70 bis 79 Jahre": {
        "männlich": 1318,
        "weiblich": 1366
      },
      "80 bis 89 Jahre": {
        "männlich": 1145,
        "weiblich": 1868
      },
      "über 90 Jahre": {
        "männlich": 265,
        "weiblich": 960
      }
    },
    "Entwicklung der Zahl der positiv auf COVID-19 getesteten Personen nach Bezirken": {
      "Altona": {
        "Fallzahlen": 7011
      },
      "Bergedorf": {
        "Fallzahlen": 3477
      },
      "Eimsbüttel": {
        "Fallzahlen": 5829
      },
      "Hamburg Mitte": {
        "Fallzahlen": 11317
      },
      "Hamburg Nord": {
        "Fallzahlen": 7055
      },
      "Harburg": {
        "Fallzahlen": 5125
      },
      "Wandsbek": {
        "Fallzahlen": 12235
      }
    }
  },
  "20210303000034": {
    "Bestätigte Fälle": 52232,
    "Erstimpfungen": 102636,
    "Zweitimpfungen": 53887,
    "Todesfälle": 1278,
    "Patienten in klinischer Behandlung": {
      "Stationär gesamt": 269,
      "Normalstation gesamt": 184,
      "Normalstation aus Hamburg": 149,
      "Intensiv gesamt": 85,
      "Intensiv aus Hamburg": 69
    },
    "Verteilung der Infizierten nach Alter und Geschlecht": {
      "bis 5 Jahre": {
        "männlich": 691,
        "weiblich": 593
      },
      "unbekannt": 408,
      "6 bis 14 Jahre": {
        "männlich": 1519,
        "weiblich": 1388
      },
      "15 bis 19 Jahre": {
        "männlich": 1501,
        "weiblich": 1487
      },
      "20 bis 29 Jahre": {
        "männlich": 4869,
        "weiblich": 5049
      },
      "30 bis 39 Jahre": {
        "männlich": 4481,
        "weiblich": 4734
      },
      "40 bis 49 Jahre": {
        "männlich": 3588,
        "weiblich": 3936
      },
      "50 bis 59 Jahre": {
        "männlich": 3599,
        "weiblich": 3593
      },
      "60 bis 69 Jahre": {
        "männlich": 1923,
        "weiblich": 1768
      },
      "70 bis 79 Jahre": {
        "männlich": 1318,
        "weiblich": 1366
      },
      "80 bis 89 Jahre": {
        "männlich": 1145,
        "weiblich": 1868
      },
      "über 90 Jahre": {
        "männlich": 265,
        "weiblich": 960
      }
    },
    "Entwicklung der Zahl der positiv auf COVID-19 getesteten Personen nach Bezirken": {
      "Altona": {
        "Fallzahlen": 7011
      },
      "Bergedorf": {
        "Fallzahlen": 3477
      },
      "Eimsbüttel": {
        "Fallzahlen": 5829
      },
      "Hamburg Mitte": {
        "Fallzahlen": 11317
      },
      "Hamburg Nord": {
        "Fallzahlen": 7055
      },
      "Harburg": {
        "Fallzahlen": 5125
      },
      "Wandsbek": {
        "Fallzahlen": 12235
      }
    }
  },
  "20210304004218": {
    "Bestätigte Fälle": 52466,
    "Erstimpfungen": 104938,
    "Zweitimpfungen": 54960,
    "Todesfälle": 1287,
    "Patienten in klinischer Behandlung": {
      "Stationär gesamt": 257,
      "Normalstation gesamt": 179,
      "Normalstation aus Hamburg": 136,
      "Intensiv gesamt": 78,
      "Intensiv aus Hamburg": 64
    },
    "Verteilung der Infizierten nach Alter und Geschlecht": {
      "bis 5 Jahre": {
        "männlich": 691,
        "weiblich": 593
      },
      "unbekannt": 408,
      "6 bis 14 Jahre": {
        "männlich": 1519,
        "weiblich": 1388
      },
      "15 bis 19 Jahre": {
        "männlich": 1501,
        "weiblich": 1487
      },
      "20 bis 29 Jahre": {
        "männlich": 4869,
        "weiblich": 5049
      },
      "30 bis 39 Jahre": {
        "männlich": 4481,
        "weiblich": 4734
      },
      "40 bis 49 Jahre": {
        "männlich": 3588,
        "weiblich": 3936
      },
      "50 bis 59 Jahre": {
        "männlich": 3599,
        "weiblich": 3593
      },
      "60 bis 69 Jahre": {
        "männlich": 1923,
        "weiblich": 1768
      },
      "70 bis 79 Jahre": {
        "männlich": 1318,
        "weiblich": 1366
      },
      "80 bis 89 Jahre": {
        "männlich": 1145,
        "weiblich": 1868
      },
      "über 90 Jahre": {
        "männlich": 265,
        "weiblich": 960
      }
    },
    "Entwicklung der Zahl der positiv auf COVID-19 getesteten Personen nach Bezirken": {
      "Altona": {
        "Fallzahlen": 7011
      },
      "Bergedorf": {
        "Fallzahlen": 3477
      },
      "Eimsbüttel": {
        "Fallzahlen": 5829
      },
      "Hamburg Mitte": {
        "Fallzahlen": 11317
      },
      "Hamburg Nord": {
        "Fallzahlen": 7055
      },
      "Harburg": {
        "Fallzahlen": 5125
      },
      "Wandsbek": {
        "Fallzahlen": 12235
      }
    }
  },
  "20210307223216": {
    "Bestätigte Fälle": 53359,
    "Erstimpfungen": 115478,
    "Zweitimpfungen": 59423,
    "Todesfälle": 1312,
    "Patienten in klinischer Behandlung": {
      "Stationär gesamt": 243,
      "Normalstation gesamt": 156,
      "Normalstation aus Hamburg": 114,
      "Intensiv gesamt": 87,
      "Intensiv aus Hamburg": 71
    },
    "Verteilung der Infizierten nach Alter und Geschlecht": {
      "bis 5 Jahre": {
        "männlich": 691,
        "weiblich": 593
      },
      "unbekannt": 408,
      "6 bis 14 Jahre": {
        "männlich": 1519,
        "weiblich": 1388
      },
      "15 bis 19 Jahre": {
        "männlich": 1501,
        "weiblich": 1487
      },
      "20 bis 29 Jahre": {
        "männlich": 4869,
        "weiblich": 5049
      },
      "30 bis 39 Jahre": {
        "männlich": 4481,
        "weiblich": 4734
      },
      "40 bis 49 Jahre": {
        "männlich": 3588,
        "weiblich": 3936
      },
      "50 bis 59 Jahre": {
        "männlich": 3599,
        "weiblich": 3593
      },
      "60 bis 69 Jahre": {
        "männlich": 1923,
        "weiblich": 1768
      },
      "70 bis 79 Jahre": {
        "männlich": 1318,
        "weiblich": 1366
      },
      "80 bis 89 Jahre": {
        "männlich": 1145,
        "weiblich": 1868
      },
      "über 90 Jahre": {
        "männlich": 265,
        "weiblich": 960
      }
    },
    "Entwicklung der Zahl der positiv auf COVID-19 getesteten Personen nach Bezirken": {
      "Altona": {
        "Fallzahlen": 7011
      },
      "Bergedorf": {
        "Fallzahlen": 3477
      },
      "Eimsbüttel": {
        "Fallzahlen": 5829
      },
      "Hamburg Mitte": {
        "Fallzahlen": 11317
      },
      "Hamburg Nord": {
        "Fallzahlen": 7055
      },
      "Harburg": {
        "Fallzahlen": 5125
      },
      "Wandsbek": {
        "Fallzahlen": 12235
      }
    }
  },
  "20210308080712": {
    "Bestätigte Fälle": 53359,
    "Erstimpfungen": 115478,
    "Zweitimpfungen": 59423,
    "Todesfälle": 1312,
    "Patienten in klinischer Behandlung": {
      "Stationär gesamt": 243,
      "Normalstation gesamt": 156,
      "Normalstation aus Hamburg": 114,
      "Intensiv gesamt": 87,
      "Intensiv aus Hamburg": 71
    },
    "Verteilung der Infizierten nach Alter und Geschlecht": {
      "bis 5 Jahre": {
        "männlich": 691,
        "weiblich": 593
      },
      "unbekannt": 408,
      "6 bis 14 Jahre": {
        "männlich": 1519,
        "weiblich": 1388
      },
      "15 bis 19 Jahre": {
        "männlich": 1501,
        "weiblich": 1487
      },
      "20 bis 29 Jahre": {
        "männlich": 4869,
        "weiblich": 5049
      },
      "30 bis 39 Jahre": {
        "männlich": 4481,
        "weiblich": 4734
      },
      "40 bis 49 Jahre": {
        "männlich": 3588,
        "weiblich": 3936
      },
      "50 bis 59 Jahre": {
        "männlich": 3599,
        "weiblich": 3593
      },
      "60 bis 69 Jahre": {
        "männlich": 1923,
        "weiblich": 1768
      },
      "70 bis 79 Jahre": {
        "männlich": 1318,
        "weiblich": 1366
      },
      "80 bis 89 Jahre": {
        "männlich": 1145,
        "weiblich": 1868
      },
      "über 90 Jahre": {
        "männlich": 265,
        "weiblich": 960
      }
    },
    "Entwicklung der Zahl der positiv auf COVID-19 getesteten Personen nach Bezirken": {
      "Altona": {
        "Fallzahlen": 7011
      },
      "Bergedorf": {
        "Fallzahlen": 3477
      },
      "Eimsbüttel": {
        "Fallzahlen": 5829
      },
      "Hamburg Mitte": {
        "Fallzahlen": 11317
      },
      "Hamburg Nord": {
        "Fallzahlen": 7055
      },
      "Harburg": {
        "Fallzahlen": 5125
      },
      "Wandsbek": {
        "Fallzahlen": 12235
      }
    }
  },
  "20210309145537": {
    "Bestätigte Fälle": 53758,
    "Erstimpfungen": 125553,
    "Zweitimpfungen": 62862,
    "Todesfälle": 1312,
    "Patienten in klinischer Behandlung": {
      "Stationär gesamt": 259,
      "Normalstation gesamt": 167,
      "Normalstation aus Hamburg": 131,
      "Intensiv gesamt": 92,
      "Intensiv aus Hamburg": 75
    },
    "Verteilung der Infizierten nach Alter und Geschlecht": {
      "bis 5 Jahre": {
        "männlich": 738,
        "weiblich": 632
      },
      "unbekannt": 409,
      "6 bis 14 Jahre": {
        "männlich": 1577,
        "weiblich": 1441
      },
      "15 bis 19 Jahre": {
        "männlich": 1535,
        "weiblich": 1532
      },
      "20 bis 29 Jahre": {
        "männlich": 4994,
        "weiblich": 5166
      },
      "30 bis 39 Jahre": {
        "männlich": 4639,
        "weiblich": 4866
      },
      "40 bis 49 Jahre": {
        "männlich": 3721,
        "weiblich": 4052
      },
      "50 bis 59 Jahre": {
        "männlich": 3710,
        "weiblich": 3683
      },
      "60 bis 69 Jahre": {
        "männlich": 1984,
        "weiblich": 1834
      },
      "70 bis 79 Jahre": {
        "männlich": 1354,
        "weiblich": 1394
      },
      "80 bis 89 Jahre": {
        "männlich": 1160,
        "weiblich": 1899
      },
      "über 90 Jahre": {
        "männlich": 268,
        "weiblich": 967
      }
    },
    "Entwicklung der Zahl der positiv auf COVID-19 getesteten Personen nach Bezirken": {
      "Altona": {
        "Fallzahlen": 7179
      },
      "Bergedorf": {
        "Fallzahlen": 3575
      },
      "Eimsbüttel": {
        "Fallzahlen": 5965
      },
      "Hamburg Mitte": {
        "Fallzahlen": 11657
      },
      "Hamburg Nord": {
        "Fallzahlen": 7259
      },
      "Harburg": {
        "Fallzahlen": 5370
      },
      "Wandsbek": {
        "Fallzahlen": 12550
      }
    }
  },
  "20210310003042": {
    "Bestätigte Fälle": 53758,
    "Erstimpfungen": 125553,
    "Zweitimpfungen": 62862,
    "Todesfälle": 1312,
    "Patienten in klinischer Behandlung": {
      "Stationär gesamt": 259,
      "Normalstation gesamt": 167,
      "Normalstation aus Hamburg": 131,
      "Intensiv gesamt": 92,
      "Intensiv aus Hamburg": 75
    },
    "Verteilung der Infizierten nach Alter und Geschlecht": {
      "bis 5 Jahre": {
        "männlich": 738,
        "weiblich": 632
      },
      "unbekannt": 409,
      "6 bis 14 Jahre": {
        "männlich": 1577,
        "weiblich": 1441
      },
      "15 bis 19 Jahre": {
        "männlich": 1535,
        "weiblich": 1532
      },
      "20 bis 29 Jahre": {
        "männlich": 4994,
        "weiblich": 5166
      },
      "30 bis 39 Jahre": {
        "männlich": 4639,
        "weiblich": 4866
      },
      "40 bis 49 Jahre": {
        "männlich": 3721,
        "weiblich": 4052
      },
      "50 bis 59 Jahre": {
        "männlich": 3710,
        "weiblich": 3683
      },
      "60 bis 69 Jahre": {
        "männlich": 1984,
        "weiblich": 1834
      },
      "70 bis 79 Jahre": {
        "männlich": 1354,
        "weiblich": 1394
      },
      "80 bis 89 Jahre": {
        "männlich": 1160,
        "weiblich": 1899
      },
      "über 90 Jahre": {
        "männlich": 268,
        "weiblich": 967
      }
    },
    "Entwicklung der Zahl der positiv auf COVID-19 getesteten Personen nach Bezirken": {
      "Altona": {
        "Fallzahlen": 7179
      },
      "Bergedorf": {
        "Fallzahlen": 3575
      },
      "Eimsbüttel": {
        "Fallzahlen": 5965
      },
      "Hamburg Mitte": {
        "Fallzahlen": 11657
      },
      "Hamburg Nord": {
        "Fallzahlen": 7259
      },
      "Harburg": {
        "Fallzahlen": 5370
      },
      "Wandsbek": {
        "Fallzahlen": 12550
      }
    }
  },
  "20210311143032": {
    "Bestätigte Fälle": 54264,
    "Erstimpfungen": 135475,
    "Zweitimpfungen": 65116,
    "Todesfälle": 1314,
    "Patienten in klinischer Behandlung": {
      "Stationär gesamt": 261,
      "Normalstation gesamt": 163,
      "Normalstation aus Hamburg": 136,
      "Intensiv gesamt": 98,
      "Intensiv aus Hamburg": 81
    },
    "Verteilung der Infizierten nach Alter und Geschlecht": {
      "bis 5 Jahre": {
        "männlich": 738,
        "weiblich": 632
      },
      "unbekannt": 409,
      "6 bis 14 Jahre": {
        "männlich": 1577,
        "weiblich": 1441
      },
      "15 bis 19 Jahre": {
        "männlich": 1535,
        "weiblich": 1532
      },
      "20 bis 29 Jahre": {
        "männlich": 4994,
        "weiblich": 5166
      },
      "30 bis 39 Jahre": {
        "männlich": 4639,
        "weiblich": 4866
      },
      "40 bis 49 Jahre": {
        "männlich": 3721,
        "weiblich": 4052
      },
      "50 bis 59 Jahre": {
        "männlich": 3710,
        "weiblich": 3683
      },
      "60 bis 69 Jahre": {
        "männlich": 1984,
        "weiblich": 1834
      },
      "70 bis 79 Jahre": {
        "männlich": 1354,
        "weiblich": 1394
      },
      "80 bis 89 Jahre": {
        "männlich": 1160,
        "weiblich": 1899
      },
      "über 90 Jahre": {
        "männlich": 268,
        "weiblich": 967
      }
    },
    "Entwicklung der Zahl der positiv auf COVID-19 getesteten Personen nach Bezirken": {
      "Altona": {
        "Fallzahlen": 7179
      },
      "Bergedorf": {
        "Fallzahlen": 3575
      },
      "Eimsbüttel": {
        "Fallzahlen": 5965
      },
      "Hamburg Mitte": {
        "Fallzahlen": 11657
      },
      "Hamburg Nord": {
        "Fallzahlen": 7259
      },
      "Harburg": {
        "Fallzahlen": 5370
      },
      "Wandsbek": {
        "Fallzahlen": 12550
      }
    }
  },
  "20210313144358": {
    "Bestätigte Fälle": 54813,
    "Erstimpfungen": 144087,
    "Zweitimpfungen": 67723,
    "Todesfälle": 1328,
    "Patienten in klinischer Behandlung": {
      "Stationär gesamt": 233,
      "Normalstation gesamt": 133,
      "Normalstation aus Hamburg": 111,
      "Intensiv gesamt": 100,
      "Intensiv aus Hamburg": 84
    },
    "Verteilung der Infizierten nach Alter und Geschlecht": {
      "bis 5 Jahre": {
        "männlich": 738,
        "weiblich": 632
      },
      "unbekannt": 409,
      "6 bis 14 Jahre": {
        "männlich": 1577,
        "weiblich": 1441
      },
      "15 bis 19 Jahre": {
        "männlich": 1535,
        "weiblich": 1532
      },
      "20 bis 29 Jahre": {
        "männlich": 4994,
        "weiblich": 5166
      },
      "30 bis 39 Jahre": {
        "männlich": 4639,
        "weiblich": 4866
      },
      "40 bis 49 Jahre": {
        "männlich": 3721,
        "weiblich": 4052
      },
      "50 bis 59 Jahre": {
        "männlich": 3710,
        "weiblich": 3683
      },
      "60 bis 69 Jahre": {
        "männlich": 1984,
        "weiblich": 1834
      },
      "70 bis 79 Jahre": {
        "männlich": 1354,
        "weiblich": 1394
      },
      "80 bis 89 Jahre": {
        "männlich": 1160,
        "weiblich": 1899
      },
      "über 90 Jahre": {
        "männlich": 268,
        "weiblich": 967
      }
    },
    "Entwicklung der Zahl der positiv auf COVID-19 getesteten Personen nach Bezirken": {
      "Altona": {
        "Fallzahlen": 7179
      },
      "Bergedorf": {
        "Fallzahlen": 3575
      },
      "Eimsbüttel": {
        "Fallzahlen": 5965
      },
      "Hamburg Mitte": {
        "Fallzahlen": 11657
      },
      "Hamburg Nord": {
        "Fallzahlen": 7259
      },
      "Harburg": {
        "Fallzahlen": 5370
      },
      "Wandsbek": {
        "Fallzahlen": 12550
      }
    }
  },
  "20210314154119": {
    "Bestätigte Fälle": 55007,
    "Erstimpfungen": 144087,
    "Zweitimpfungen": 67723,
    "Todesfälle": 1332,
    "Patienten in klinischer Behandlung": {
      "Stationär gesamt": 233,
      "Normalstation gesamt": 133,
      "Normalstation aus Hamburg": 111,
      "Intensiv gesamt": 100,
      "Intensiv aus Hamburg": 84
    },
    "Verteilung der Infizierten nach Alter und Geschlecht": {
      "bis 5 Jahre": {
        "männlich": 738,
        "weiblich": 632
      },
      "unbekannt": 409,
      "6 bis 14 Jahre": {
        "männlich": 1577,
        "weiblich": 1441
      },
      "15 bis 19 Jahre": {
        "männlich": 1535,
        "weiblich": 1532
      },
      "20 bis 29 Jahre": {
        "männlich": 4994,
        "weiblich": 5166
      },
      "30 bis 39 Jahre": {
        "männlich": 4639,
        "weiblich": 4866
      },
      "40 bis 49 Jahre": {
        "männlich": 3721,
        "weiblich": 4052
      },
      "50 bis 59 Jahre": {
        "männlich": 3710,
        "weiblich": 3683
      },
      "60 bis 69 Jahre": {
        "männlich": 1984,
        "weiblich": 1834
      },
      "70 bis 79 Jahre": {
        "männlich": 1354,
        "weiblich": 1394
      },
      "80 bis 89 Jahre": {
        "männlich": 1160,
        "weiblich": 1899
      },
      "über 90 Jahre": {
        "männlich": 268,
        "weiblich": 967
      }
    },
    "Entwicklung der Zahl der positiv auf COVID-19 getesteten Personen nach Bezirken": {
      "Altona": {
        "Fallzahlen": 7179
      },
      "Bergedorf": {
        "Fallzahlen": 3575
      },
      "Eimsbüttel": {
        "Fallzahlen": 5965
      },
      "Hamburg Mitte": {
        "Fallzahlen": 11657
      },
      "Hamburg Nord": {
        "Fallzahlen": 7259
      },
      "Harburg": {
        "Fallzahlen": 5370
      },
      "Wandsbek": {
        "Fallzahlen": 12550
      }
    }
  },
  "20210315184515": {
    "Bestätigte Fälle": 55275,
    "Erstimpfungen": 151821,
    "Zweitimpfungen": 70301,
    "Todesfälle": 1332,
    "Patienten in klinischer Behandlung": {
      "Stationär gesamt": 233,
      "Normalstation gesamt": 133,
      "Normalstation aus Hamburg": 111,
      "Intensiv gesamt": 100,
      "Intensiv aus Hamburg": 84
    },
    "Verteilung der Infizierten nach Alter und Geschlecht": {
      "bis 5 Jahre": {
        "männlich": 738,
        "weiblich": 632
      },
      "unbekannt": 409,
      "6 bis 14 Jahre": {
        "männlich": 1577,
        "weiblich": 1441
      },
      "15 bis 19 Jahre": {
        "männlich": 1535,
        "weiblich": 1532
      },
      "20 bis 29 Jahre": {
        "männlich": 4994,
        "weiblich": 5166
      },
      "30 bis 39 Jahre": {
        "männlich": 4639,
        "weiblich": 4866
      },
      "40 bis 49 Jahre": {
        "männlich": 3721,
        "weiblich": 4052
      },
      "50 bis 59 Jahre": {
        "männlich": 3710,
        "weiblich": 3683
      },
      "60 bis 69 Jahre": {
        "männlich": 1984,
        "weiblich": 1834
      },
      "70 bis 79 Jahre": {
        "männlich": 1354,
        "weiblich": 1394
      },
      "80 bis 89 Jahre": {
        "männlich": 1160,
        "weiblich": 1899
      },
      "über 90 Jahre": {
        "männlich": 268,
        "weiblich": 967
      }
    },
    "Entwicklung der Zahl der positiv auf COVID-19 getesteten Personen nach Bezirken": {
      "Altona": {
        "Fallzahlen": 7179
      },
      "Bergedorf": {
        "Fallzahlen": 3575
      },
      "Eimsbüttel": {
        "Fallzahlen": 5965
      },
      "Hamburg Mitte": {
        "Fallzahlen": 11657
      },
      "Hamburg Nord": {
        "Fallzahlen": 7259
      },
      "Harburg": {
        "Fallzahlen": 5370
      },
      "Wandsbek": {
        "Fallzahlen": 12550
      }
    }
  },
  "20210315184522": {
    "Bestätigte Fälle": 55275,
    "Erstimpfungen": 151821,
    "Zweitimpfungen": 70301,
    "Todesfälle": 1332,
    "Patienten in klinischer Behandlung": {
      "Stationär gesamt": 233,
      "Normalstation gesamt": 133,
      "Normalstation aus Hamburg": 111,
      "Intensiv gesamt": 100,
      "Intensiv aus Hamburg": 84
    },
    "Verteilung der Infizierten nach Alter und Geschlecht": {
      "bis 5 Jahre": {
        "männlich": 738,
        "weiblich": 632
      },
      "unbekannt": 409,
      "6 bis 14 Jahre": {
        "männlich": 1577,
        "weiblich": 1441
      },
      "15 bis 19 Jahre": {
        "männlich": 1535,
        "weiblich": 1532
      },
      "20 bis 29 Jahre": {
        "männlich": 4994,
        "weiblich": 5166
      },
      "30 bis 39 Jahre": {
        "männlich": 4639,
        "weiblich": 4866
      },
      "40 bis 49 Jahre": {
        "männlich": 3721,
        "weiblich": 4052
      },
      "50 bis 59 Jahre": {
        "männlich": 3710,
        "weiblich": 3683
      },
      "60 bis 69 Jahre": {
        "männlich": 1984,
        "weiblich": 1834
      },
      "70 bis 79 Jahre": {
        "männlich": 1354,
        "weiblich": 1394
      },
      "80 bis 89 Jahre": {
        "männlich": 1160,
        "weiblich": 1899
      },
      "über 90 Jahre": {
        "männlich": 268,
        "weiblich": 967
      }
    },
    "Entwicklung der Zahl der positiv auf COVID-19 getesteten Personen nach Bezirken": {
      "Altona": {
        "Fallzahlen": 7179
      },
      "Bergedorf": {
        "Fallzahlen": 3575
      },
      "Eimsbüttel": {
        "Fallzahlen": 5965
      },
      "Hamburg Mitte": {
        "Fallzahlen": 11657
      },
      "Hamburg Nord": {
        "Fallzahlen": 7259
      },
      "Harburg": {
        "Fallzahlen": 5370
      },
      "Wandsbek": {
        "Fallzahlen": 12550
      }
    }
  },
  "20210316113115": {
    "Bestätigte Fälle": 55484,
    "Erstimpfungen": 155380,
    "Zweitimpfungen": 71770,
    "Todesfälle": 1332,
    "Patienten in klinischer Behandlung": {
      "Stationär gesamt": 262,
      "Normalstation gesamt": 161,
      "Normalstation aus Hamburg": 138,
      "Intensiv gesamt": 101,
      "Intensiv aus Hamburg": 85
    },
    "Verteilung der Infizierten nach Alter und Geschlecht": {
      "bis 5 Jahre": {
        "männlich": 798,
        "weiblich": 659
      },
      "unbekannt": 437,
      "6 bis 14 Jahre": {
        "männlich": 1643,
        "weiblich": 1488
      },
      "15 bis 19 Jahre": {
        "männlich": 1585,
        "weiblich": 1585
      },
      "20 bis 29 Jahre": {
        "männlich": 5142,
        "weiblich": 5332
      },
      "30 bis 39 Jahre": {
        "männlich": 4810,
        "weiblich": 5031
      },
      "40 bis 49 Jahre": {
        "männlich": 3861,
        "weiblich": 4167
      },
      "50 bis 59 Jahre": {
        "männlich": 3841,
        "weiblich": 3792
      },
      "60 bis 69 Jahre": {
        "männlich": 2047,
        "weiblich": 1891
      },
      "70 bis 79 Jahre": {
        "männlich": 1401,
        "weiblich": 1421
      },
      "80 bis 89 Jahre": {
        "männlich": 1168,
        "weiblich": 1928
      },
      "über 90 Jahre": {
        "männlich": 269,
        "weiblich": 979
      }
    },
    "Entwicklung der Zahl der positiv auf COVID-19 getesteten Personen nach Bezirken": {
      "Altona": {
        "Fallzahlen": 7379
      },
      "Bergedorf": {
        "Fallzahlen": 3702
      },
      "Eimsbüttel": {
        "Fallzahlen": 6114
      },
      "Hamburg Mitte": {
        "Fallzahlen": 12074
      },
      "Hamburg Nord": {
        "Fallzahlen": 7452
      },
      "Harburg": {
        "Fallzahlen": 5676
      },
      "Wandsbek": {
        "Fallzahlen": 12878
      }
    }
  },
  "20210316140806": {
    "Bestätigte Fälle": 55484,
    "Erstimpfungen": 155380,
    "Zweitimpfungen": 71770,
    "Todesfälle": 1332,
    "Patienten in klinischer Behandlung": {
      "Stationär gesamt": 262,
      "Normalstation gesamt": 161,
      "Normalstation aus Hamburg": 138,
      "Intensiv gesamt": 101,
      "Intensiv aus Hamburg": 85
    },
    "Verteilung der Infizierten nach Alter und Geschlecht": {
      "bis 5 Jahre": {
        "männlich": 798,
        "weiblich": 659
      },
      "unbekannt": 437,
      "6 bis 14 Jahre": {
        "männlich": 1643,
        "weiblich": 1488
      },
      "15 bis 19 Jahre": {
        "männlich": 1585,
        "weiblich": 1585
      },
      "20 bis 29 Jahre": {
        "männlich": 5142,
        "weiblich": 5332
      },
      "30 bis 39 Jahre": {
        "männlich": 4810,
        "weiblich": 5031
      },
      "40 bis 49 Jahre": {
        "männlich": 3861,
        "weiblich": 4167
      },
      "50 bis 59 Jahre": {
        "männlich": 3841,
        "weiblich": 3792
      },
      "60 bis 69 Jahre": {
        "männlich": 2047,
        "weiblich": 1891
      },
      "70 bis 79 Jahre": {
        "männlich": 1401,
        "weiblich": 1421
      },
      "80 bis 89 Jahre": {
        "männlich": 1168,
        "weiblich": 1928
      },
      "über 90 Jahre": {
        "männlich": 269,
        "weiblich": 979
      }
    },
    "Entwicklung der Zahl der positiv auf COVID-19 getesteten Personen nach Bezirken": {
      "Altona": {
        "Fallzahlen": 7379
      },
      "Bergedorf": {
        "Fallzahlen": 3702
      },
      "Eimsbüttel": {
        "Fallzahlen": 6114
      },
      "Hamburg Mitte": {
        "Fallzahlen": 12074
      },
      "Hamburg Nord": {
        "Fallzahlen": 7452
      },
      "Harburg": {
        "Fallzahlen": 5676
      },
      "Wandsbek": {
        "Fallzahlen": 12878
      }
    }
  },
  "20210317020046": {
    "Bestätigte Fälle": 55484,
    "Erstimpfungen": 155380,
    "Zweitimpfungen": 71770,
    "Todesfälle": 1332,
    "Patienten in klinischer Behandlung": {
      "Stationär gesamt": 262,
      "Normalstation gesamt": 161,
      "Normalstation aus Hamburg": 138,
      "Intensiv gesamt": 101,
      "Intensiv aus Hamburg": 85
    },
    "Verteilung der Infizierten nach Alter und Geschlecht": {
      "bis 5 Jahre": {
        "männlich": 798,
        "weiblich": 659
      },
      "unbekannt": 437,
      "6 bis 14 Jahre": {
        "männlich": 1643,
        "weiblich": 1488
      },
      "15 bis 19 Jahre": {
        "männlich": 1585,
        "weiblich": 1585
      },
      "20 bis 29 Jahre": {
        "männlich": 5142,
        "weiblich": 5332
      },
      "30 bis 39 Jahre": {
        "männlich": 4810,
        "weiblich": 5031
      },
      "40 bis 49 Jahre": {
        "männlich": 3861,
        "weiblich": 4167
      },
      "50 bis 59 Jahre": {
        "männlich": 3841,
        "weiblich": 3792
      },
      "60 bis 69 Jahre": {
        "männlich": 2047,
        "weiblich": 1891
      },
      "70 bis 79 Jahre": {
        "männlich": 1401,
        "weiblich": 1421
      },
      "80 bis 89 Jahre": {
        "männlich": 1168,
        "weiblich": 1928
      },
      "über 90 Jahre": {
        "männlich": 269,
        "weiblich": 979
      }
    },
    "Entwicklung der Zahl der positiv auf COVID-19 getesteten Personen nach Bezirken": {
      "Altona": {
        "Fallzahlen": 7379
      },
      "Bergedorf": {
        "Fallzahlen": 3702
      },
      "Eimsbüttel": {
        "Fallzahlen": 6114
      },
      "Hamburg Mitte": {
        "Fallzahlen": 12074
      },
      "Hamburg Nord": {
        "Fallzahlen": 7452
      },
      "Harburg": {
        "Fallzahlen": 5676
      },
      "Wandsbek": {
        "Fallzahlen": 12878
      }
    }
  },
  "20210317170012": {
    "Bestätigte Fälle": 55877,
    "Erstimpfungen": 158446,
    "Zweitimpfungen": 72962,
    "Todesfälle": 1337,
    "Patienten in klinischer Behandlung": {
      "Stationär gesamt": 260,
      "Normalstation gesamt": 163,
      "Normalstation aus Hamburg": 138,
      "Intensiv gesamt": 97,
      "Intensiv aus Hamburg": 80
    },
    "Verteilung der Infizierten nach Alter und Geschlecht": {
      "bis 5 Jahre": {
        "männlich": 798,
        "weiblich": 659
      },
      "unbekannt": 437,
      "6 bis 14 Jahre": {
        "männlich": 1643,
        "weiblich": 1488
      },
      "15 bis 19 Jahre": {
        "männlich": 1585,
        "weiblich": 1585
      },
      "20 bis 29 Jahre": {
        "männlich": 5142,
        "weiblich": 5332
      },
      "30 bis 39 Jahre": {
        "männlich": 4810,
        "weiblich": 5031
      },
      "40 bis 49 Jahre": {
        "männlich": 3861,
        "weiblich": 4167
      },
      "50 bis 59 Jahre": {
        "männlich": 3841,
        "weiblich": 3792
      },
      "60 bis 69 Jahre": {
        "männlich": 2047,
        "weiblich": 1891
      },
      "70 bis 79 Jahre": {
        "männlich": 1401,
        "weiblich": 1421
      },
      "80 bis 89 Jahre": {
        "männlich": 1168,
        "weiblich": 1928
      },
      "über 90 Jahre": {
        "männlich": 269,
        "weiblich": 979
      }
    },
    "Entwicklung der Zahl der positiv auf COVID-19 getesteten Personen nach Bezirken": {
      "Altona": {
        "Fallzahlen": 7379
      },
      "Bergedorf": {
        "Fallzahlen": 3702
      },
      "Eimsbüttel": {
        "Fallzahlen": 6114
      },
      "Hamburg Mitte": {
        "Fallzahlen": 12074
      },
      "Hamburg Nord": {
        "Fallzahlen": 7452
      },
      "Harburg": {
        "Fallzahlen": 5676
      },
      "Wandsbek": {
        "Fallzahlen": 12878
      }
    }
  },
  "20210319044153": {
    "Bestätigte Fälle": 56266,
    "Erstimpfungen": 161839,
    "Zweitimpfungen": 74137,
    "Todesfälle": 1337,
    "Patienten in klinischer Behandlung": {
      "Stationär gesamt": 250,
      "Normalstation gesamt": 158,
      "Normalstation aus Hamburg": 136,
      "Intensiv gesamt": 92,
      "Intensiv aus Hamburg": 78
    },
    "Verteilung der Infizierten nach Alter und Geschlecht": {
      "bis 5 Jahre": {
        "männlich": 798,
        "weiblich": 659
      },
      "unbekannt": 437,
      "6 bis 14 Jahre": {
        "männlich": 1643,
        "weiblich": 1488
      },
      "15 bis 19 Jahre": {
        "männlich": 1585,
        "weiblich": 1585
      },
      "20 bis 29 Jahre": {
        "männlich": 5142,
        "weiblich": 5332
      },
      "30 bis 39 Jahre": {
        "männlich": 4810,
        "weiblich": 5031
      },
      "40 bis 49 Jahre": {
        "männlich": 3861,
        "weiblich": 4167
      },
      "50 bis 59 Jahre": {
        "männlich": 3841,
        "weiblich": 3792
      },
      "60 bis 69 Jahre": {
        "männlich": 2047,
        "weiblich": 1891
      },
      "70 bis 79 Jahre": {
        "männlich": 1401,
        "weiblich": 1421
      },
      "80 bis 89 Jahre": {
        "männlich": 1168,
        "weiblich": 1928
      },
      "über 90 Jahre": {
        "männlich": 269,
        "weiblich": 979
      }
    },
    "Entwicklung der Zahl der positiv auf COVID-19 getesteten Personen nach Bezirken": {
      "Altona": {
        "Fallzahlen": 7379
      },
      "Bergedorf": {
        "Fallzahlen": 3702
      },
      "Eimsbüttel": {
        "Fallzahlen": 6114
      },
      "Hamburg Mitte": {
        "Fallzahlen": 12074
      },
      "Hamburg Nord": {
        "Fallzahlen": 7452
      },
      "Harburg": {
        "Fallzahlen": 5676
      },
      "Wandsbek": {
        "Fallzahlen": 12878
      }
    }
  },
  "20210321081547": {
    "Bestätigte Fälle": 57002,
    "Erstimpfungen": 167855,
    "Zweitimpfungen": 76805,
    "Todesfälle": 1343,
    "Patienten in klinischer Behandlung": {
      "Stationär gesamt": 241,
      "Normalstation gesamt": 151,
      "Normalstation aus Hamburg": 131,
      "Intensiv gesamt": 90,
      "Intensiv aus Hamburg": 76
    },
    "Verteilung der Infizierten nach Alter und Geschlecht": {
      "bis 5 Jahre": {
        "männlich": 798,
        "weiblich": 659
      },
      "unbekannt": 437,
      "6 bis 14 Jahre": {
        "männlich": 1643,
        "weiblich": 1488
      },
      "15 bis 19 Jahre": {
        "männlich": 1585,
        "weiblich": 1585
      },
      "20 bis 29 Jahre": {
        "männlich": 5142,
        "weiblich": 5332
      },
      "30 bis 39 Jahre": {
        "männlich": 4810,
        "weiblich": 5031
      },
      "40 bis 49 Jahre": {
        "männlich": 3861,
        "weiblich": 4167
      },
      "50 bis 59 Jahre": {
        "männlich": 3841,
        "weiblich": 3792
      },
      "60 bis 69 Jahre": {
        "männlich": 2047,
        "weiblich": 1891
      },
      "70 bis 79 Jahre": {
        "männlich": 1401,
        "weiblich": 1421
      },
      "80 bis 89 Jahre": {
        "männlich": 1168,
        "weiblich": 1928
      },
      "über 90 Jahre": {
        "männlich": 269,
        "weiblich": 979
      }
    },
    "Entwicklung der Zahl der positiv auf COVID-19 getesteten Personen nach Bezirken": {
      "Altona": {
        "Fallzahlen": 7379
      },
      "Bergedorf": {
        "Fallzahlen": 3702
      },
      "Eimsbüttel": {
        "Fallzahlen": 6114
      },
      "Hamburg Mitte": {
        "Fallzahlen": 12074
      },
      "Hamburg Nord": {
        "Fallzahlen": 7452
      },
      "Harburg": {
        "Fallzahlen": 5676
      },
      "Wandsbek": {
        "Fallzahlen": 12878
      }
    }
  },
  "20210322123321": {
    "Bestätigte Fälle": 57462,
    "Erstimpfungen": 173735,
    "Zweitimpfungen": 79430,
    "Todesfälle": 1349,
    "Patienten in klinischer Behandlung": {
      "Stationär gesamt": 241,
      "Normalstation gesamt": 151,
      "Normalstation aus Hamburg": 131,
      "Intensiv gesamt": 90,
      "Intensiv aus Hamburg": 76
    },
    "Verteilung der Infizierten nach Alter und Geschlecht": {
      "bis 5 Jahre": {
        "männlich": 798,
        "weiblich": 659
      },
      "unbekannt": 437,
      "6 bis 14 Jahre": {
        "männlich": 1643,
        "weiblich": 1488
      },
      "15 bis 19 Jahre": {
        "männlich": 1585,
        "weiblich": 1585
      },
      "20 bis 29 Jahre": {
        "männlich": 5142,
        "weiblich": 5332
      },
      "30 bis 39 Jahre": {
        "männlich": 4810,
        "weiblich": 5031
      },
      "40 bis 49 Jahre": {
        "männlich": 3861,
        "weiblich": 4167
      },
      "50 bis 59 Jahre": {
        "männlich": 3841,
        "weiblich": 3792
      },
      "60 bis 69 Jahre": {
        "männlich": 2047,
        "weiblich": 1891
      },
      "70 bis 79 Jahre": {
        "männlich": 1401,
        "weiblich": 1421
      },
      "80 bis 89 Jahre": {
        "männlich": 1168,
        "weiblich": 1928
      },
      "über 90 Jahre": {
        "männlich": 269,
        "weiblich": 979
      }
    },
    "Entwicklung der Zahl der positiv auf COVID-19 getesteten Personen nach Bezirken": {
      "Altona": {
        "Fallzahlen": 7379
      },
      "Bergedorf": {
        "Fallzahlen": 3702
      },
      "Eimsbüttel": {
        "Fallzahlen": 6114
      },
      "Hamburg Mitte": {
        "Fallzahlen": 12074
      },
      "Hamburg Nord": {
        "Fallzahlen": 7452
      },
      "Harburg": {
        "Fallzahlen": 5676
      },
      "Wandsbek": {
        "Fallzahlen": 12878
      }
    }
  },
  "20210324040556": {
    "Bestätigte Fälle": 57759,
    "Erstimpfungen": 176452,
    "Zweitimpfungen": 80632,
    "Todesfälle": 1355,
    "Patienten in klinischer Behandlung": {
      "Stationär gesamt": 237,
      "Normalstation gesamt": 154,
      "Normalstation aus Hamburg": 134,
      "Intensiv gesamt": 83,
      "Intensiv aus Hamburg": 74
    },
    "Verteilung der Infizierten nach Alter und Geschlecht": {
      "bis 5 Jahre": {
        "männlich": 879,
        "weiblich": 699
      },
      "unbekannt": 442,
      "6 bis 14 Jahre": {
        "männlich": 1739,
        "weiblich": 1569
      },
      "15 bis 19 Jahre": {
        "männlich": 1653,
        "weiblich": 1650
      },
      "20 bis 29 Jahre": {
        "männlich": 5335,
        "weiblich": 5522
      },
      "30 bis 39 Jahre": {
        "männlich": 5006,
        "weiblich": 5242
      },
      "40 bis 49 Jahre": {
        "männlich": 4034,
        "weiblich": 4322
      },
      "50 bis 59 Jahre": {
        "männlich": 4017,
        "weiblich": 3943
      },
      "60 bis 69 Jahre": {
        "männlich": 2151,
        "weiblich": 1961
      },
      "70 bis 79 Jahre": {
        "männlich": 1443,
        "weiblich": 1462
      },
      "80 bis 89 Jahre": {
        "männlich": 1186,
        "weiblich": 1952
      },
      "über 90 Jahre": {
        "männlich": 272,
        "weiblich": 983
      }
    },
    "Entwicklung der Zahl der positiv auf COVID-19 getesteten Personen nach Bezirken": {
      "Altona": {
        "Fallzahlen": 7645
      },
      "Bergedorf": {
        "Fallzahlen": 3833
      },
      "Eimsbüttel": {
        "Fallzahlen": 6334
      },
      "Hamburg Mitte": {
        "Fallzahlen": 12572
      },
      "Hamburg Nord": {
        "Fallzahlen": 7761
      },
      "Harburg": {
        "Fallzahlen": 5953
      },
      "Wandsbek": {
        "Fallzahlen": 13364
      }
    }
  },
  "20210325043244": {
    "Bestätigte Fälle": 58159,
    "Erstimpfungen": 179265,
    "Zweitimpfungen": 81708,
    "Todesfälle": 1358,
    "Patienten in klinischer Behandlung": {
      "Stationär gesamt": 242,
      "Normalstation gesamt": 158,
      "Normalstation aus Hamburg": 134,
      "Intensiv gesamt": 84,
      "Intensiv aus Hamburg": 71
    },
    "Verteilung der Infizierten nach Alter und Geschlecht": {
      "bis 5 Jahre": {
        "männlich": 879,
        "weiblich": 699
      },
      "unbekannt": 442,
      "6 bis 14 Jahre": {
        "männlich": 1739,
        "weiblich": 1569
      },
      "15 bis 19 Jahre": {
        "männlich": 1653,
        "weiblich": 1650
      },
      "20 bis 29 Jahre": {
        "männlich": 5335,
        "weiblich": 5522
      },
      "30 bis 39 Jahre": {
        "männlich": 5006,
        "weiblich": 5242
      },
      "40 bis 49 Jahre": {
        "männlich": 4034,
        "weiblich": 4322
      },
      "50 bis 59 Jahre": {
        "männlich": 4017,
        "weiblich": 3943
      },
      "60 bis 69 Jahre": {
        "männlich": 2151,
        "weiblich": 1961
      },
      "70 bis 79 Jahre": {
        "männlich": 1443,
        "weiblich": 1462
      },
      "80 bis 89 Jahre": {
        "männlich": 1186,
        "weiblich": 1952
      },
      "über 90 Jahre": {
        "männlich": 272,
        "weiblich": 983
      }
    },
    "Entwicklung der Zahl der positiv auf COVID-19 getesteten Personen nach Bezirken": {
      "Altona": {
        "Fallzahlen": 7645
      },
      "Bergedorf": {
        "Fallzahlen": 3833
      },
      "Eimsbüttel": {
        "Fallzahlen": 6334
      },
      "Hamburg Mitte": {
        "Fallzahlen": 12572
      },
      "Hamburg Nord": {
        "Fallzahlen": 7761
      },
      "Harburg": {
        "Fallzahlen": 5953
      },
      "Wandsbek": {
        "Fallzahlen": 13364
      }
    }
  },
  "20210325180141": {
    "Bestätigte Fälle": 58708,
    "Erstimpfungen": 182998,
    "Zweitimpfungen": 82939,
    "Todesfälle": 1364,
    "Patienten in klinischer Behandlung": {
      "Stationär gesamt": 253,
      "Normalstation gesamt": 167,
      "Normalstation aus Hamburg": 139,
      "Intensiv gesamt": 86,
      "Intensiv aus Hamburg": 75
    },
    "Verteilung der Infizierten nach Alter und Geschlecht": {
      "bis 5 Jahre": {
        "männlich": 879,
        "weiblich": 699
      },
      "unbekannt": 442,
      "6 bis 14 Jahre": {
        "männlich": 1739,
        "weiblich": 1569
      },
      "15 bis 19 Jahre": {
        "männlich": 1653,
        "weiblich": 1650
      },
      "20 bis 29 Jahre": {
        "männlich": 5335,
        "weiblich": 5522
      },
      "30 bis 39 Jahre": {
        "männlich": 5006,
        "weiblich": 5242
      },
      "40 bis 49 Jahre": {
        "männlich": 4034,
        "weiblich": 4322
      },
      "50 bis 59 Jahre": {
        "männlich": 4017,
        "weiblich": 3943
      },
      "60 bis 69 Jahre": {
        "männlich": 2151,
        "weiblich": 1961
      },
      "70 bis 79 Jahre": {
        "männlich": 1443,
        "weiblich": 1462
      },
      "80 bis 89 Jahre": {
        "männlich": 1186,
        "weiblich": 1952
      },
      "über 90 Jahre": {
        "männlich": 272,
        "weiblich": 983
      }
    },
    "Entwicklung der Zahl der positiv auf COVID-19 getesteten Personen nach Bezirken": {
      "Altona": {
        "Fallzahlen": 7645
      },
      "Bergedorf": {
        "Fallzahlen": 3833
      },
      "Eimsbüttel": {
        "Fallzahlen": 6334
      },
      "Hamburg Mitte": {
        "Fallzahlen": 12572
      },
      "Hamburg Nord": {
        "Fallzahlen": 7761
      },
      "Harburg": {
        "Fallzahlen": 5953
      },
      "Wandsbek": {
        "Fallzahlen": 13364
      }
    }
  },
  "20210326133734": {
    "Bestätigte Fälle": 59251,
    "Erstimpfungen": 186502,
    "Zweitimpfungen": 84229,
    "Todesfälle": 1369,
    "Patienten in klinischer Behandlung": {
      "Stationär gesamt": 252,
      "Normalstation gesamt": 166,
      "Normalstation aus Hamburg": 146,
      "Intensiv gesamt": 86,
      "Intensiv aus Hamburg": 76
    },
    "Verteilung der Infizierten nach Alter und Geschlecht": {
      "bis 5 Jahre": {
        "männlich": 879,
        "weiblich": 699
      },
      "unbekannt": 442,
      "6 bis 14 Jahre": {
        "männlich": 1739,
        "weiblich": 1569
      },
      "15 bis 19 Jahre": {
        "männlich": 1653,
        "weiblich": 1650
      },
      "20 bis 29 Jahre": {
        "männlich": 5335,
        "weiblich": 5522
      },
      "30 bis 39 Jahre": {
        "männlich": 5006,
        "weiblich": 5242
      },
      "40 bis 49 Jahre": {
        "männlich": 4034,
        "weiblich": 4322
      },
      "50 bis 59 Jahre": {
        "männlich": 4017,
        "weiblich": 3943
      },
      "60 bis 69 Jahre": {
        "männlich": 2151,
        "weiblich": 1961
      },
      "70 bis 79 Jahre": {
        "männlich": 1443,
        "weiblich": 1462
      },
      "80 bis 89 Jahre": {
        "männlich": 1186,
        "weiblich": 1952
      },
      "über 90 Jahre": {
        "männlich": 272,
        "weiblich": 983
      }
    },
    "Entwicklung der Zahl der positiv auf COVID-19 getesteten Personen nach Bezirken": {
      "Altona": {
        "Fallzahlen": 7645
      },
      "Bergedorf": {
        "Fallzahlen": 3833
      },
      "Eimsbüttel": {
        "Fallzahlen": 6334
      },
      "Hamburg Mitte": {
        "Fallzahlen": 12572
      },
      "Hamburg Nord": {
        "Fallzahlen": 7761
      },
      "Harburg": {
        "Fallzahlen": 5953
      },
      "Wandsbek": {
        "Fallzahlen": 13364
      }
    }
  },
  "20210326184610": {
    "Bestätigte Fälle": 59251,
    "Erstimpfungen": 186502,
    "Zweitimpfungen": 84229,
    "Todesfälle": 1369,
    "Patienten in klinischer Behandlung": {
      "Stationär gesamt": 252,
      "Normalstation gesamt": 166,
      "Normalstation aus Hamburg": 146,
      "Intensiv gesamt": 86,
      "Intensiv aus Hamburg": 76
    },
    "Verteilung der Infizierten nach Alter und Geschlecht": {
      "bis 5 Jahre": {
        "männlich": 879,
        "weiblich": 699
      },
      "unbekannt": 442,
      "6 bis 14 Jahre": {
        "männlich": 1739,
        "weiblich": 1569
      },
      "15 bis 19 Jahre": {
        "männlich": 1653,
        "weiblich": 1650
      },
      "20 bis 29 Jahre": {
        "männlich": 5335,
        "weiblich": 5522
      },
      "30 bis 39 Jahre": {
        "männlich": 5006,
        "weiblich": 5242
      },
      "40 bis 49 Jahre": {
        "männlich": 4034,
        "weiblich": 4322
      },
      "50 bis 59 Jahre": {
        "männlich": 4017,
        "weiblich": 3943
      },
      "60 bis 69 Jahre": {
        "männlich": 2151,
        "weiblich": 1961
      },
      "70 bis 79 Jahre": {
        "männlich": 1443,
        "weiblich": 1462
      },
      "80 bis 89 Jahre": {
        "männlich": 1186,
        "weiblich": 1952
      },
      "über 90 Jahre": {
        "männlich": 272,
        "weiblich": 983
      }
    },
    "Entwicklung der Zahl der positiv auf COVID-19 getesteten Personen nach Bezirken": {
      "Altona": {
        "Fallzahlen": 7645
      },
      "Bergedorf": {
        "Fallzahlen": 3833
      },
      "Eimsbüttel": {
        "Fallzahlen": 6334
      },
      "Hamburg Mitte": {
        "Fallzahlen": 12572
      },
      "Hamburg Nord": {
        "Fallzahlen": 7761
      },
      "Harburg": {
        "Fallzahlen": 5953
      },
      "Wandsbek": {
        "Fallzahlen": 13364
      }
    }
  },
  "20210328224841": {
    "Bestätigte Fälle": 59990,
    "Erstimpfungen": 191233,
    "Zweitimpfungen": 85507,
    "Todesfälle": 1372,
    "Patienten in klinischer Behandlung": {
      "Stationär gesamt": 274,
      "Normalstation gesamt": 188,
      "Normalstation aus Hamburg": 166,
      "Intensiv gesamt": 86,
      "Intensiv aus Hamburg": 76
    },
    "Verteilung der Infizierten nach Alter und Geschlecht": {
      "bis 5 Jahre": {
        "männlich": 879,
        "weiblich": 699
      },
      "unbekannt": 442,
      "6 bis 14 Jahre": {
        "männlich": 1739,
        "weiblich": 1569
      },
      "15 bis 19 Jahre": {
        "männlich": 1653,
        "weiblich": 1650
      },
      "20 bis 29 Jahre": {
        "männlich": 5335,
        "weiblich": 5522
      },
      "30 bis 39 Jahre": {
        "männlich": 5006,
        "weiblich": 5242
      },
      "40 bis 49 Jahre": {
        "männlich": 4034,
        "weiblich": 4322
      },
      "50 bis 59 Jahre": {
        "männlich": 4017,
        "weiblich": 3943
      },
      "60 bis 69 Jahre": {
        "männlich": 2151,
        "weiblich": 1961
      },
      "70 bis 79 Jahre": {
        "männlich": 1443,
        "weiblich": 1462
      },
      "80 bis 89 Jahre": {
        "männlich": 1186,
        "weiblich": 1952
      },
      "über 90 Jahre": {
        "männlich": 272,
        "weiblich": 983
      }
    },
    "Entwicklung der Zahl der positiv auf COVID-19 getesteten Personen nach Bezirken": {
      "Altona": {
        "Fallzahlen": 7645
      },
      "Bergedorf": {
        "Fallzahlen": 3833
      },
      "Eimsbüttel": {
        "Fallzahlen": 6334
      },
      "Hamburg Mitte": {
        "Fallzahlen": 12572
      },
      "Hamburg Nord": {
        "Fallzahlen": 7761
      },
      "Harburg": {
        "Fallzahlen": 5953
      },
      "Wandsbek": {
        "Fallzahlen": 13364
      }
    }
  }
}